opentelemetry_exporter_oci_monitoring/__init__.py
opentelemetry_exporter_oci_monitoring/converter.py
opentelemetry_exporter_oci_monitoring/py.typed
opentelemetry_exporter_oci_monitoring/utils.py
opentelemetry_exporter_oci_monitoring-0.6.0.dist-info/LICENSE
opentelemetry_exporter_oci_monitoring-0.6.0.dist-info/METADATA
opentelemetry_exporter_oci_monitoring-0.6.0.dist-info/WHEEL
opentelemetry_exporter_oci_monitoring-0.6.0.dist-info/RECORD
