Metadata-Version: 2.1
Name: opentelemetry-exporter-oci-monitoring
Version: 0.6.0
Summary: A Python OpenTelemetry exporter for the OCI Monitoring Service.
Home-page: https://github.com/bjoern-reetz/opentelemetry-python-exporter-oci-monitoring
License: MIT
Keywords: opentelemetry,exporter,oci,monitoring
Author: Björn Reetz
Author-email: git@bjoern-reetz.de
Requires-Python: >=3.8,<4.0
Classifier: Development Status :: 4 - Beta
Classifier: Framework :: OpenTelemetry :: Exporters
Classifier: Intended Audience :: Developers
Classifier: License :: OSI Approved :: MIT License
Classifier: Operating System :: OS Independent
Classifier: Programming Language :: Python :: 3
Classifier: Programming Language :: Python :: 3.8
Classifier: Programming Language :: Python :: 3.9
Classifier: Programming Language :: Python :: 3.10
Classifier: Programming Language :: Python :: 3.11
Classifier: Programming Language :: Python :: 3.12
Classifier: Topic :: Software Development :: Libraries :: Python Modules
Classifier: Topic :: System :: Monitoring
Classifier: Typing :: Typed
Requires-Dist: oci (>=2.129.0,<3.0.0)
Requires-Dist: opentelemetry-sdk (>=1.25.0,<2.0.0)
Project-URL: Documentation, https://github.com/bjoern-reetz/opentelemetry-python-exporter-oci-monitoring
Project-URL: Repository, https://github.com/bjoern-reetz/opentelemetry-python-exporter-oci-monitoring
